prologging/__init__.py
prologging/logger.py
prologging/output.py
prologging/handler/api.py
prologging/handler/file.py
ProLogging-0.1.3.dist-info/METADATA
ProLogging-0.1.3.dist-info/WHEEL
ProLogging-0.1.3.dist-info/top_level.txt
ProLogging-0.1.3.dist-info/RECORD
